jsonui.py
jsonui-0.2.dist-info/LICENSE
jsonui-0.2.dist-info/METADATA
jsonui-0.2.dist-info/WHEEL
jsonui-0.2.dist-info/entry_points.txt
jsonui-0.2.dist-info/top_level.txt
jsonui-0.2.dist-info/RECORD
